{
    "tweet_id": 1366994021101408260,
    "retweet_id": 0,
    "quote_id": 1367018722976665605,
    "reply_id": 0,
    "conversation_id": 1366994021101408260,
    "source_id": 0,
    "date": "2021-03-03 06:09:06",
    "author": {
        "id": 1169777952143245313,
        "name": "MOMOTETSU_INFO",
        "nick": "「桃太郎電鉄」 公式アカウント",
        "date": "2019-09-06 01:04:39",
        "profile_banner": "https://pbs.twimg.com/profile_banners/1169777952143245313/1767680422",
        "favourites_count": 120,
        "followers_count": 116235,
        "friends_count": 139,
        "listed_count": 279,
        "media_count": 661,
        "statuses_count": 1874,
        "location": "",
        "verified": false,
        "protected": false,
        "profile_image": "https://pbs.twimg.com/profile_images/2008423370770255872/ivDJU5FW.jpg",
        "url": "https://www.konami.com/games/momotetsu/2/",
        "description": "『桃太郎電鉄２ ～あなたの町も きっとある～ 東日本編＋西日本編』Switch 2、Switch向けに、2025年11月13日発売！\n\n#桃鉄2\n\n商品サービス問合わせhttps://konami.jp/3nJNipg\nSNS利用方針https://konami.jp/3iV7XCY"
    },
    "user": {
        "id": 1098214790600617985,
        "name": "suganami_mirei",
        "nick": "菅波 美玲",
        "date": "2019-02-20 13:36:24",
        "profile_banner": "https://pbs.twimg.com/profile_banners/1098214790600617985/1765861504",
        "favourites_count": 8437,
        "followers_count": 125041,
        "friends_count": 52,
        "listed_count": 2719,
        "media_count": 2579,
        "statuses_count": 8462,
        "location": "",
        "verified": false,
        "protected": false,
        "profile_image": "https://pbs.twimg.com/profile_images/2000794234329423875/yDnjXgFv.jpg",
        "url": "https://not-equal-me.jp",
        "description": "O型、2000年2月5日生まれ、みずがめ座、福島県出身。指原莉乃プロデュースのアイドル「≠ME(ノットイコールミー)」 Instagram → http://instagram.com/suganami_mirei_"
    },
    "lang": "ja",
    "source": "Twitter for Advertisers.",
    "sensitive": null,
    "sensitive_flags": null,
    "favorite_count": 3211,
    "quote_count": 139,
    "reply_count": 18,
    "retweet_count": 1276,
    "bookmark_count": 41,
    "view_count": 0,
    "hashtags": [
        "陣内智則",
        "ヒャダイン",
        "狩野英孝",
        "菅波美玲",
        "並木万里菜",
        "ベルモンド・バンデラス",
        "Masuo",
        "南明奈",
        "桃鉄GP",
        "桃鉄令和"
    ],
    "content": "🍑🚂速報🍑🚂\n\n 3/21(日)開催決定！\n「桃鉄グランプリ」エキシビションマッチ \n\n豪華著名人によるエキシビションマッチを生配信！🎥\n\nMC:#陣内智則🍑\n特別解説:#ヒャダイン\n\n出演者(第1弾発表)\n#狩野英孝\n#菅波美玲\n#並木万里菜\n#ベルモンド・バンデラス\n#Masuo\n#南明奈\n\n#桃鉄GP #桃鉄令和",
    "quote_by": "suganami_mirei",
    "count": 0,
    "category": "twitter",
    "subcategory": "timeline"
}
