{
    "tweet_id": 1427330260656279559,
    "retweet_id": 0,
    "quote_id": 1427527609131307016,
    "reply_id": 0,
    "conversation_id": 1427330260656279559,
    "source_id": 0,
    "date": "2021-08-16 18:03:47",
    "author": {
        "id": 4174180574,
        "name": "TVer_official",
        "nick": "TVer",
        "date": "2015-11-09 01:40:34",
        "profile_banner": "https://pbs.twimg.com/profile_banners/4174180574/1772017207",
        "favourites_count": 5,
        "followers_count": 265069,
        "friends_count": 9,
        "listed_count": 930,
        "media_count": 81150,
        "statuses_count": 190719,
        "location": "いつでもどこでも完全無料でご視聴できます。",
        "verified": false,
        "protected": false,
        "profile_image": "https://pbs.twimg.com/profile_images/2026613165371568129/iINSC9W2.png",
        "url": "http://tver.jp/",
        "description": "国内最大級の無料動画配信サービス #TVer の公式アカウントです。\n\n全番組の配信新着情報▶️@TVer_info"
    },
    "user": {
        "id": 1098214790600617985,
        "name": "suganami_mirei",
        "nick": "菅波 美玲",
        "date": "2019-02-20 13:36:24",
        "profile_banner": "https://pbs.twimg.com/profile_banners/1098214790600617985/1765861504",
        "favourites_count": 8438,
        "followers_count": 125246,
        "friends_count": 52,
        "listed_count": 2717,
        "media_count": 2579,
        "statuses_count": 8463,
        "location": "",
        "verified": false,
        "protected": false,
        "profile_image": "https://pbs.twimg.com/profile_images/2000794234329423875/yDnjXgFv.jpg",
        "url": "https://not-equal-me.jp",
        "description": "O型、2000年2月5日生まれ、みずがめ座、福島県出身。指原莉乃プロデュースのアイドル「≠ME(ノットイコールミー)」 Instagram → http://instagram.com/suganami_mirei_"
    },
    "lang": "ja",
    "source": "Twitter for iPhone",
    "sensitive": false,
    "sensitive_flags": null,
    "favorite_count": 464,
    "quote_count": 9,
    "reply_count": 0,
    "retweet_count": 91,
    "bookmark_count": 1,
    "view_count": 0,
    "hashtags": [
        "イコノイどーですか",
        "イコラブ",
        "ノイミー",
        "ニューヨーク",
        "TVer"
    ],
    "mentions": [
        {
            "id": 1365887974735405058,
            "name": "ikonoi_tbs",
            "nick": "イコノイ、どーですか？"
        }
    ],
    "content": "TBS「イコノイ､どーですか?」\n#18 オフィシャルブック連動企画!｢インパクト写真撮影会｣前編\n\n#イコノイどーですか #イコラブ #ノイミー #ニューヨーク #TVer @ikonoi_tbs\nhttps://tver.jp/corner/f0081137",
    "quote_by": "suganami_mirei",
    "count": 0,
    "category": "twitter",
    "subcategory": "timeline"
}
