{
    "tweet_id": 1763738612678730137,
    "retweet_id": 0,
    "quote_id": 1763807628474613994,
    "reply_id": 0,
    "conversation_id": 1763738612678730137,
    "source_id": 0,
    "date": "2024-03-02 01:30:28",
    "author": {
        "id": 1098216249295699968,
        "name": "suzuki_hitomi_",
        "nick": "鈴木 瞳美",
        "date": "2019-02-20 13:42:12",
        "profile_banner": "https://pbs.twimg.com/profile_banners/1098216249295699968/1765861473",
        "favourites_count": 5015,
        "followers_count": 185336,
        "friends_count": 49,
        "listed_count": 3057,
        "media_count": 1630,
        "statuses_count": 4726,
        "location": "",
        "verified": false,
        "protected": false,
        "profile_image": "https://pbs.twimg.com/profile_images/2000794106445037568/WQJG9H88.jpg",
        "url": "https://not-equal-me.jp",
        "description": "2001年4月13日生まれ、おひつじ座、東京都出身、B型。指原莉乃プロデュースのアイドル「 ≠ME(ノットイコールミー )」Instagram ‣ https://www.instagram.com/suzuki_hitomi__"
    },
    "user": {
        "id": 1098214790600617985,
        "name": "suganami_mirei",
        "nick": "菅波 美玲",
        "date": "2019-02-20 13:36:24",
        "profile_banner": "https://pbs.twimg.com/profile_banners/1098214790600617985/1765861504",
        "favourites_count": 8438,
        "followers_count": 125246,
        "friends_count": 52,
        "listed_count": 2717,
        "media_count": 2579,
        "statuses_count": 8463,
        "location": "",
        "verified": false,
        "protected": false,
        "profile_image": "https://pbs.twimg.com/profile_images/2000794234329423875/yDnjXgFv.jpg",
        "url": "https://not-equal-me.jp",
        "description": "O型、2000年2月5日生まれ、みずがめ座、福島県出身。指原莉乃プロデュースのアイドル「≠ME(ノットイコールミー)」 Instagram → http://instagram.com/suganami_mirei_"
    },
    "lang": "ja",
    "source": "Twitter for iPhone",
    "sensitive": false,
    "sensitive_flags": null,
    "favorite_count": 1148,
    "quote_count": 8,
    "reply_count": 110,
    "retweet_count": 94,
    "bookmark_count": 3,
    "view_count": 315507,
    "content": "＂マイナビ TGC 2024 S/S＂\n本日出演させていただきます💭\n\n緊張でドキドキだよ〜\n素敵な機会とってもうれしいです…！！\n\nAbemaにて生配信もあります👼🏻ﾞ\n‣ https://abema.tv/channels/special-plus-2/slots/AYCLG9NsJSZ4wh\n\n精一杯がんばります！✊🏻\n見守ってくれたらうれしいな💭",
    "quote_by": "suganami_mirei",
    "count": 0,
    "category": "twitter",
    "subcategory": "timeline"
}
